Metadata-Version: 2.4
Name: CASSIA
Version: 0.3.18
Summary: CASSIA (Cell type Annotation using Specialized System with Integrated AI) is a Python package for automated cell type annotation in single-cell RNA sequencing data using large language models.
Home-page: https://github.com/elliotxe/CASSIA
Author: Elliot Yixuan Xie
Author-email: xie227@wisc.edu
Classifier: Development Status :: 3 - Alpha
Classifier: Intended Audience :: Science/Research
Classifier: Topic :: Scientific/Engineering :: Bio-Informatics
Classifier: License :: OSI Approved :: MIT License
Classifier: Programming Language :: Python :: 3
Classifier: Programming Language :: Python :: 3.9
Classifier: Programming Language :: Python :: 3.10
Classifier: Programming Language :: Python :: 3.11
Classifier: Programming Language :: Python :: 3.12
Classifier: Programming Language :: Python :: 3.13
Requires-Python: >=3.9
Requires-Dist: numpy>=1.21.0
Requires-Dist: pandas>=1.3.0
Requires-Dist: openai>=1.0.0
Requires-Dist: anthropic>=0.3.0
Requires-Dist: requests>=2.25.0
Requires-Dist: matplotlib>=3.3.0
Requires-Dist: seaborn>=0.11.0
Requires-Dist: mygene>=3.2.0
Dynamic: author
Dynamic: author-email
Dynamic: classifier
Dynamic: description
Dynamic: description-content-type
Dynamic: home-page
Dynamic: requires-dist
Dynamic: requires-python
Dynamic: summary
